dpsn_plugin_gamesdk/dpsn_plugin.py
dpsn_plugin_gamesdk-0.0.1.dist-info/METADATA
dpsn_plugin_gamesdk-0.0.1.dist-info/WHEEL
dpsn_plugin_gamesdk-0.0.1.dist-info/RECORD
