Metadata-Version: 2.3
Name: dpsn-plugin-gamesdk
Version: 0.0.1
Summary: DPSN Plugin for Python SDK for GAME by Virtuals
Author: dpsn-dev
Author-email: sanil@dpsn.org
Requires-Python: >=3.9
Classifier: Programming Language :: Python :: 3
Classifier: Programming Language :: Python :: 3.9
Classifier: Programming Language :: Python :: 3.10
Classifier: Programming Language :: Python :: 3.11
Classifier: License :: OSI Approved :: MIT License
Classifier: Operating System :: OS Independent
Classifier: Development Status :: 3 - Alpha
Classifier: Intended Audience :: Developers
Classifier: Topic :: Software Development :: Libraries :: Python Modules
Requires-Dist: dpsn-client (==1.0.0.post1)
Requires-Dist: game-sdk (>=0.1.1)
Project-URL: Bug Tracker, https://github.com/game-by-virtuals/game-python
Project-URL: Homepage, https://github.com/game-by-virtuals/game-python/plugins/dpsn
